{
    "version": "3.0.0",
    "summary": "Style Animations in Elm",
    "repository": "https://github.com/mdgriffith/elm-style-animation.git",
    "license": "BSD3",
    "source-directories": [
        "src"
    ],
    "exposed-modules": [
        "Animation",
        "Animation.Messenger"
    ],
    "dependencies": {
        "elm-community/list-extra": "3.1.0 <= v < 4.0.0",
        "elm-lang/animation-frame": "1.0.0 <= v < 2.0.0",
        "elm-lang/core": "4.0.0 <= v < 5.0.0",
        "elm-lang/html": "1.0.0 <= v < 2.0.0",
        "elm-lang/svg": "1.0.0 <= v < 2.0.0"
    },
    "elm-version": "0.17.0 <= v < 0.18.0"
}